{
  "bg": 84, 
  "temp": "absolute", 
  "snoozeBG": 140, 
  "predBGs": {
    "aCOB": [
      84, 
      95, 
      106, 
      117, 
      128, 
      138, 
      148, 
      158, 
      168, 
      177, 
      185, 
      194, 
      201, 
      208, 
      214, 
      220, 
      224, 
      228, 
      231, 
      234, 
      236, 
      237, 
      238, 
      239, 
      240, 
      241, 
      242, 
      242, 
      242, 
      243
    ], 
    "IOB": [
      84, 
      86, 
      88, 
      90, 
      93, 
      96, 
      99, 
      102, 
      105, 
      109, 
      112, 
      116, 
      119, 
      122, 
      125, 
      128, 
      130, 
      133, 
      135, 
      136, 
      138, 
      139, 
      140, 
      141, 
      142, 
      143, 
      144, 
      144, 
      144, 
      145
    ]
  }, 
  "rate": 1.65, 
  "reason": "COB: 21, Dev: -10, BGI: 3.22, ISF: 88, Target: 109; Eventual BG 140 >= 109, temp 0.925<1.65U/hr", 
  "COB": 21, 
  "eventualBG": 140, 
  "duration": 30, 
  "tick": "+2", 
  "IOB": -0.752
}