{
  "bg": 112, 
  "temp": "absolute", 
  "snoozeBG": 91, 
  "predBGs": {
    "IOB": [
      112, 
      110, 
      108, 
      107, 
      105, 
      104, 
      103, 
      102, 
      101, 
      101, 
      101, 
      101, 
      101, 
      102, 
      103, 
      104, 
      105, 
      106, 
      107, 
      109, 
      110, 
      111, 
      112, 
      113, 
      114, 
      115, 
      116, 
      117, 
      118, 
      119, 
      120, 
      120, 
      121, 
      121, 
      122, 
      122, 
      123
    ]
  }, 
  "reason": "COB: 0, Dev: -12, BGI: -0.18, ISF: 89, Target: 110; Eventual BG 91 < 110, setting -0.025U/hr, but 27m left and 0 ~ req 0U/hr: no action required", 
  "COB": 0, 
  "eventualBG": 91, 
  "tick": -2, 
  "IOB": 0.102
}