[
  {
    "created_at": "2016-10-27T16:11:51.467Z", 
    "mmtune": {
      "scanDetails": [
        [
          "916.564", 
          5, 
          -75
        ], 
        [
          "916.588", 
          5, 
          -71
        ], 
        [
          "916.612", 
          5, 
          -72
        ], 
        [
          "916.636", 
          5, 
          -70
        ], 
        [
          "916.660", 
          5, 
          -65
        ], 
        [
          "916.684", 
          5, 
          -66
        ], 
        [
          "916.708", 
          5, 
          -75
        ]
      ], 
      "setFreq": 916.66, 
      "usedDefault": false, 
      "timestamp": "2016-10-27T16:09:02.000Z"
    }, 
    "pump": {
      "battery": {
        "status": "normal", 
        "voltage": 1.49
      }, 
      "status": {
        "status": "normal", 
        "timestamp": "2016-10-27T16:09:23.000Z", 
        "bolusing": false, 
        "suspended": false
      }, 
      "reservoir": 58.75, 
      "clock": "2016-10-27T09:09:40-07:00"
    }, 
    "openaps": {
      "suggested": {
        "bg": 111, 
        "temp": "absolute", 
        "snoozeBG": 97, 
        "timestamp": "2016-10-27T16:11:20.000Z", 
        "rate": 0.45, 
        "reason": "COB: 0, Dev: 8, BGI: -1.37, ISF: 74, Target: 101; Eventual BG 97 < 101, setting 0.45U/hr", 
        "COB": 0, 
        "eventualBG": 97, 
        "duration": 30, 
        "tick": "+0", 
        "IOB": 0.303
      }, 
      "iob": {
        "netbasalinsulin": 0.25, 
        "timestamp": "2016-10-27T16:09:40.000Z", 
        "activity": 0.0037, 
        "basaliob": 0.197, 
        "hightempinsulin": 0.65, 
        "bolussnooze": 0, 
        "iob": 0.303
      }, 
      "enacted": {
        "bg": 111, 
        "temp": "absolute", 
        "snoozeBG": 97, 
        "recieved": true, 
        "predBGs": {
          "IOB": [
            111, 
            111, 
            111, 
            111, 
            111, 
            111, 
            110, 
            110, 
            110, 
            109, 
            109, 
            108, 
            107, 
            107, 
            106, 
            105, 
            104, 
            103, 
            102, 
            102, 
            101, 
            100, 
            99, 
            99, 
            98, 
            97, 
            97, 
            96, 
            96, 
            96, 
            95
          ]
        }, 
        "reason": "COB: 0, Dev: 8, BGI: -1.37, ISF: 74, Target: 101; Eventual BG 97 < 101, setting 0.45U/hr", 
        "rate": 0.45, 
        "COB": 0, 
        "eventualBG": 97, 
        "timestamp": "2016-10-27T16:11:43.000Z", 
        "duration": 30, 
        "tick": "+0", 
        "IOB": 0.303
      }
    }, 
    "uploader": {
      "battery": 78, 
      "batteryVoltage": 3958
    }, 
    "device": "openaps://indy-e1", 
    "_id": "5812274745ce720f18e10d56"
  }
]