{
  "bg": 97, 
  "temp": "absolute", 
  "snoozeBG": 90, 
  "recieved": true, 
  "predBGs": {
    "IOB": [
      97, 
      94, 
      92, 
      90, 
      88, 
      87, 
      85, 
      85, 
      84, 
      84, 
      84, 
      85, 
      85, 
      86, 
      87, 
      89, 
      90, 
      91, 
      92, 
      93, 
      94, 
      95, 
      96, 
      97, 
      98, 
      99, 
      99, 
      100, 
      101, 
      101, 
      102, 
      102, 
      102, 
      103
    ]
  }, 
  "reason": "COB: 0, Dev: -19, BGI: 0.35, ISF: 78, Target: 103; Eventual BG 90 < 103, setting -0.025U/hr", 
  "rate": 0.0, 
  "COB": 0, 
  "eventualBG": 90, 
  "timestamp": "2016-10-29T09:02:11.756935", 
  "duration": 30, 
  "tick": -2, 
  "IOB": -0.15
}