{
  "device": "openaps://indy-e1", 
  "pump": {
    "battery": {
      "status": "normal", 
      "voltage": 1.5
    }, 
    "status": {
      "status": "normal", 
      "timestamp": "2016-11-01T14:26:40.000Z", 
      "bolusing": false, 
      "suspended": false
    }, 
    "reservoir": 122.65, 
    "clock": "2016-11-01T07:26:59-07:00"
  }, 
  "uploader": {
    "battery": 100, 
    "batteryVoltage": 4375
  }, 
  "openaps": {
    "suggested": {
      "bg": 89, 
      "temp": "absolute", 
      "snoozeBG": 94, 
      "timestamp": "2016-11-01T14:28:30.000Z", 
      "reason": "COB: 7, Dev: 2, BGI: -0.76, ISF: 90, Target: 80; Eventual BG 72 < 80, bolus snooze: eventual BG range 72-94; setting current basal of 0.55 as temp. Setting neutral temp basal of 0.55U/hr", 
      "rate": 0.55, 
      "COB": 7, 
      "eventualBG": 72, 
      "duration": 30, 
      "tick": -4, 
      "IOB": 0.558
    }, 
    "iob": {
      "netbasalinsulin": -0.45, 
      "timestamp": "2016-11-01T14:26:59.000Z", 
      "activity": 0.0017, 
      "basaliob": -0.131, 
      "hightempinsulin": 0.1, 
      "bolussnooze": 0.389, 
      "iob": 0.558
    }, 
    "enacted": {
      "bg": 89, 
      "temp": "absolute", 
      "snoozeBG": 94, 
      "recieved": true, 
      "predBGs": {
        "COB": [
          89, 
          92, 
          95, 
          97, 
          99, 
          100, 
          100, 
          100, 
          100, 
          99, 
          98, 
          97, 
          96, 
          95, 
          93, 
          92, 
          91, 
          89, 
          88, 
          86, 
          85, 
          83, 
          82, 
          81, 
          79, 
          78, 
          77, 
          76, 
          75, 
          75, 
          74, 
          74, 
          73, 
          73, 
          73, 
          72
        ], 
        "aCOB": [
          89, 
          97, 
          104, 
          110, 
          115, 
          118, 
          120, 
          120, 
          119, 
          118, 
          115, 
          112, 
          108, 
          105, 
          102, 
          99, 
          96, 
          93, 
          90, 
          87, 
          85, 
          82, 
          80, 
          78, 
          77, 
          75, 
          74, 
          73, 
          72, 
          72, 
          71, 
          71, 
          70, 
          70, 
          70, 
          69
        ], 
        "IOB": [
          89, 
          92, 
          94, 
          96, 
          97, 
          97, 
          96, 
          95, 
          93, 
          91, 
          88, 
          85, 
          82, 
          78, 
          75, 
          72, 
          69, 
          66, 
          63, 
          60, 
          58, 
          56, 
          53, 
          52, 
          50, 
          48, 
          47, 
          46, 
          45, 
          45, 
          44, 
          44, 
          43, 
          43, 
          43, 
          43, 
          42
        ]
      }, 
      "rate": 0.55, 
      "reason": "COB: 7, Dev: 2, BGI: -0.76, ISF: 90, Target: 80; Eventual BG 72 < 80, bolus snooze: eventual BG range 72-94; setting current basal of 0.55 as temp. Setting neutral temp basal of 0.55U/hr", 
      "COB": 7, 
      "eventualBG": 72, 
      "timestamp": "2016-11-01T14:28:51.000Z", 
      "duration": 30, 
      "tick": -4, 
      "IOB": 0.558
    }
  }, 
  "mmtune": {
    "scanDetails": [
      [
        "916.540", 
        5, 
        -79
      ], 
      [
        "916.564", 
        5, 
        -66
      ], 
      [
        "916.588", 
        5, 
        -63
      ], 
      [
        "916.612", 
        5, 
        -66
      ], 
      [
        "916.636", 
        5, 
        -62
      ], 
      [
        "916.660", 
        5, 
        -64
      ], 
      [
        "916.684", 
        5, 
        -67
      ]
    ], 
    "setFreq": 916.636, 
    "timestamp": "2016-11-01T14:26:20.000Z", 
    "usedDefault": false
  }
}