{
  "device": "openaps://indy-e1", 
  "pump": {
    "battery": {
      "status": "normal", 
      "voltage": 1.42
    }, 
    "status": {
      "status": "normal", 
      "timestamp": "2016-10-17T21:45:25.000Z", 
      "bolusing": false, 
      "suspended": false
    }, 
    "reservoir": 95.425, 
    "clock": "2016-10-17T14:45:38-07:00"
  }, 
  "uploader": {
    "battery": 52, 
    "batteryVoltage": 3695
  }, 
  "openaps": {
    "suggested": {
      "bg": 147, 
      "temp": "absolute", 
      "snoozeBG": 114, 
      "timestamp": "2016-10-17T21:47:11.000Z", 
      "reason": "COB: 16, Dev: 12, BGI: -6.06, ISF: 89, Target: 110; Eventual BG 132 >= 110, 27m@0.275 = 0.124 > req 0.01+20%. Setting temp basal of 0.675U/hr", 
      "rate": 0.675, 
      "COB": 16, 
      "eventualBG": 132, 
      "duration": 30, 
      "tick": -4, 
      "IOB": 0.708
    }, 
    "iob": {
      "netbasalinsulin": 1.05, 
      "timestamp": "2016-10-17T21:45:38.000Z", 
      "activity": 0.0136, 
      "basaliob": 0.576, 
      "hightempinsulin": 1.05, 
      "bolussnooze": 0, 
      "iob": 0.708
    }, 
    "enacted": {
      "bg": 147, 
      "temp": "absolute", 
      "snoozeBG": 114, 
      "recieved": true, 
      "predBGs": {
        "COB": [
          147, 
          143, 
          139, 
          136, 
          133, 
          130, 
          127, 
          125, 
          124, 
          122, 
          121, 
          120, 
          119, 
          118, 
          117, 
          116, 
          116, 
          115, 
          115, 
          114, 
          114, 
          114, 
          115, 
          115, 
          115, 
          116, 
          117, 
          117, 
          118, 
          119, 
          120, 
          121, 
          122, 
          123, 
          124, 
          125, 
          126, 
          127, 
          128, 
          129, 
          130, 
          131, 
          132
        ], 
        "aCOB": [
          147, 
          150, 
          153, 
          156, 
          158, 
          160, 
          162, 
          164, 
          165, 
          166, 
          167, 
          167, 
          167, 
          166, 
          164, 
          163, 
          160, 
          158, 
          156, 
          154, 
          152, 
          151, 
          150, 
          149, 
          148, 
          147, 
          146, 
          146, 
          145, 
          145, 
          144, 
          144, 
          144, 
          144, 
          144, 
          143
        ], 
        "IOB": [
          147, 
          143, 
          139, 
          135, 
          131, 
          128, 
          124, 
          121, 
          118, 
          116, 
          113, 
          110, 
          108, 
          105, 
          102, 
          100, 
          98, 
          95, 
          93, 
          91, 
          90, 
          88, 
          87, 
          86, 
          85, 
          84, 
          83, 
          83, 
          82, 
          82, 
          82, 
          81
        ]
      }, 
      "rate": 0.675, 
      "reason": "COB: 16, Dev: 12, BGI: -6.06, ISF: 89, Target: 110; Eventual BG 132 >= 110, 27m@0.275 = 0.124 > req 0.01+20%. Setting temp basal of 0.675U/hr", 
      "COB": 16, 
      "eventualBG": 132, 
      "timestamp": "2016-10-17T21:47:31.000Z", 
      "duration": 30, 
      "tick": -4, 
      "IOB": 0.708
    }
  }, 
  "mmtune": {
    "scanDetails": [
      [
        "916.564", 
        5, 
        -63
      ], 
      [
        "916.588", 
        5, 
        -60
      ], 
      [
        "916.612", 
        5, 
        -61
      ], 
      [
        "916.636", 
        5, 
        -61
      ], 
      [
        "916.660", 
        5, 
        -61
      ], 
      [
        "916.684", 
        5, 
        -65
      ], 
      [
        "916.708", 
        3, 
        -82
      ]
    ], 
    "setFreq": 916.588, 
    "timestamp": "2016-10-17T21:45:04.000Z", 
    "usedDefault": false
  }
}