{
  "device": "openaps://indy-e1", 
  "pump": {
    "battery": {
      "status": "normal", 
      "voltage": 1.46
    }, 
    "status": {
      "status": "normal", 
      "timestamp": "2016-10-27T19:18:43.000Z", 
      "bolusing": false, 
      "suspended": false
    }, 
    "reservoir": 55.775, 
    "clock": "2016-10-27T12:18:59-07:00"
  }, 
  "uploader": {
    "battery": 63, 
    "batteryVoltage": 3806
  }, 
  "openaps": {
    "suggested": {
      "bg": 126, 
      "temp": "absolute", 
      "snoozeBG": 88, 
      "timestamp": "2016-10-27T19:20:25.000Z", 
      "reason": "COB: 0, Dev: -4, BGI: -2.8, ISF: 73, Target: 100; Eventual BG 88 < 100, setting 0.1U/hr", 
      "rate": 0.1, 
      "COB": 0, 
      "eventualBG": 88, 
      "duration": 30, 
      "tick": -4, 
      "IOB": 0.47
    }, 
    "iob": {
      "netbasalinsulin": 0.4, 
      "timestamp": "2016-10-27T19:18:59.000Z", 
      "activity": 0.0077, 
      "basaliob": 0.344, 
      "hightempinsulin": 0.8, 
      "bolussnooze": 0, 
      "iob": 0.47
    }, 
    "enacted": {
      "bg": 126, 
      "temp": "absolute", 
      "snoozeBG": 88, 
      "recieved": true, 
      "predBGs": {
        "IOB": [
          126, 
          122, 
          118, 
          115, 
          111, 
          108, 
          105, 
          103, 
          100, 
          98, 
          96, 
          95, 
          93, 
          92, 
          91, 
          91, 
          90, 
          89, 
          88, 
          88, 
          87, 
          87, 
          87, 
          86
        ]
      }, 
      "rate": 0.1, 
      "reason": "COB: 0, Dev: -4, BGI: -2.8, ISF: 73, Target: 100; Eventual BG 88 < 100, setting 0.1U/hr", 
      "COB": 0, 
      "eventualBG": 88, 
      "timestamp": "2016-10-27T19:20:49.000Z", 
      "duration": 30, 
      "tick": -4, 
      "IOB": 0.47
    }
  }, 
  "mmtune": {
    "scanDetails": [
      [
        "916.564", 
        5, 
        -83
      ], 
      [
        "916.588", 
        5, 
        -78
      ], 
      [
        "916.612", 
        5, 
        -78
      ], 
      [
        "916.636", 
        5, 
        -77
      ], 
      [
        "916.660", 
        5, 
        -76
      ], 
      [
        "916.684", 
        5, 
        -78
      ], 
      [
        "916.708", 
        5, 
        -85
      ]
    ], 
    "setFreq": 916.66, 
    "timestamp": "2016-10-27T19:18:22.000Z", 
    "usedDefault": false
  }
}